{
  "routes": [
    {
      "weight_typical": 366.114,
      "duration_typical": 260.004,
      "weight_name": "auto",
      "weight": 358.967,
      "duration": 254.169,
      "distance": 2045.35,
      "legs": [
        {
          "admins": [
            {
              "iso_3166_1_alpha3": "USA",
              "iso_3166_1": "US"
            }
          ],
          "incidents": [
            {
              "length": 50,
              "affected_road_names": [
                "9th Street"
              ],
              "id": "11589180127444257",
              "type": "lane_restriction",
              "congestion": {
                "value": 20
              },
              "description": "Rummelsburger Landstrasse: Bauarbeiten um Fritz-K\u00f6nig-Weg",
              "long_description": "Fahrbahnverengung von auf eine Fahrspur wegen Bauarbeiten auf der Rummelsburger Landstrasse in Richtung S\u00fcden zwischen Rummelsburger Landstrasse und Fritz-K\u00f6nig-Weg.",
              "impact": "low",
              "alertc_codes": [
                743
              ],
              "geometry_index_start": 3,
              "geometry_index_end": 8,
              "creation_time": "2022-05-11T14:10:36Z",
              "start_time": "2022-04-29T13:08:25Z",
              "end_time": "3022-05-30T21:59:00Z",
              "iso_3166_1_alpha2": "US",
              "iso_3166_1_alpha3": "USA",
              "lanes_blocked": []
            }
          ],
          "annotation": {
            "maxspeed": [
              {
                "unknown": true
              },
              {
                "unknown": true
              },
              {
                "unknown": true
              },
              {
                "unknown": true
              },
              {
                "unknown": true
              },
              {
                "unknown": true
              },
              {
                "speed": 40,
                "unit": "km\/h"
              },
              {
                "speed": 40,
                "unit": "km\/h"
              },
              {
                "speed": 40,
                "unit": "km\/h"
              },
              {
                "speed": 40,
                "unit": "km\/h"
              },
              {
                "speed": 40,
                "unit": "km\/h"
              },
              {
                "speed": 40,
                "unit": "km\/h"
              },
              {
                "speed": 40,
                "unit": "km\/h"
              },
              {
                "speed": 40,
                "unit": "km\/h"
              },
              {
                "speed": 40,
                "unit": "km\/h"
              },
              {
                "speed": 40,
                "unit": "km\/h"
              },
              {
                "speed": 40,
                "unit": "km\/h"
              },
              {
                "speed": 40,
                "unit": "km\/h"
              },
              {
                "speed": 40,
                "unit": "km\/h"
              },
              {
                "speed": 40,
                "unit": "km\/h"
              },
              {
                "speed": 40,
                "unit": "km\/h"
              },
              {
                "speed": 40,
                "unit": "km\/h"
              },
              {
                "speed": 40,
                "unit": "km\/h"
              },
              {
                "speed": 40,
                "unit": "km\/h"
              },
              {
                "speed": 40,
                "unit": "km\/h"
              },
              {
                "speed": 40,
                "unit": "km\/h"
              },
              {
                "speed": 40,
                "unit": "km\/h"
              },
              {
                "speed": 40,
                "unit": "km\/h"
              },
              {
                "speed": 40,
                "unit": "km\/h"
              },
              {
                "speed": 40,
                "unit": "km\/h"
              },
              {
                "speed": 40,
                "unit": "km\/h"
              },
              {
                "speed": 40,
                "unit": "km\/h"
              },
              {
                "speed": 40,
                "unit": "km\/h"
              },
              {
                "speed": 40,
                "unit": "km\/h"
              },
              {
                "speed": 40,
                "unit": "km\/h"
              },
              {
                "speed": 40,
                "unit": "km\/h"
              },
              {
                "speed": 48,
                "unit": "km\/h"
              },
              {
                "speed": 48,
                "unit": "km\/h"
              },
              {
                "speed": 48,
                "unit": "km\/h"
              },
              {
                "speed": 48,
                "unit": "km\/h"
              },
              {
                "speed": 48,
                "unit": "km\/h"
              },
              {
                "speed": 48,
                "unit": "km\/h"
              },
              {
                "speed": 48,
                "unit": "km\/h"
              },
              {
                "speed": 48,
                "unit": "km\/h"
              },
              {
                "unknown": true
              },
              {
                "unknown": true
              },
              {
                "unknown": true
              },
              {
                "unknown": true
              },
              {
                "unknown": true
              }
            ],
            "speed": [
              4.2,
              4.2,
              10.6,
              10.6,
              9.4,
              9.4,
              6.1,
              9.7,
              9.7,
              9.7,
              9.7,
              7.5,
              7.5,
              7.5,
              11.4,
              11.4,
              11.4,
              12.8,
              12.8,
              12.8,
              6.9,
              6.9,
              10.3,
              5.8,
              10,
              10.8,
              11.7,
              11.7,
              11.7,
              8.9,
              10.3,
              10.3,
              9.7,
              11.1,
              11.1,
              5.6,
              11.9,
              11.9,
              13.9,
              13.9,
              13.6,
              13.6,
              16.1,
              11.7,
              9.7,
              9.4,
              9.7,
              9.7,
              9.4
            ],
            "distance": [
              27.2,
              8.9,
              13.3,
              11.4,
              10.7,
              109.9,
              121.8,
              6.9,
              4,
              100.3,
              10.6,
              11.2,
              101.6,
              10.2,
              10.1,
              126.8,
              11,
              9.3,
              102,
              11.1,
              11.5,
              110.5,
              63.9,
              58.7,
              64.3,
              48.2,
              18.8,
              3.7,
              14.6,
              113.9,
              19.6,
              45.6,
              64.3,
              26.4,
              38.4,
              64.4,
              48.6,
              31.5,
              9.7,
              30.5,
              50.8,
              13.8,
              61.4,
              122.1,
              34.1,
              29.9,
              7.8,
              8,
              9.2
            ],
            "duration": [
              6.518,
              2.144,
              1.258,
              1.077,
              1.134,
              11.638,
              19.931,
              0.709,
              0.409,
              10.317,
              1.093,
              1.5,
              13.541,
              1.362,
              0.89,
              11.132,
              0.969,
              0.727,
              7.985,
              0.87,
              1.654,
              15.913,
              6.217,
              10.058,
              6.432,
              4.449,
              1.614,
              0.32,
              1.252,
              12.814,
              1.903,
              4.442,
              6.616,
              2.379,
              3.459,
              11.6,
              4.068,
              2.64,
              0.695,
              2.199,
              3.735,
              1.013,
              3.81,
              10.466,
              3.505,
              3.165,
              0.801,
              0.826,
              0.975
            ]
          },
          "weight_typical": 366.114,
          "duration_typical": 260.004,
          "weight": 358.967,
          "duration": 254.169,
          "steps": [
            {
              "voiceInstructions": [
                {
                  "ssmlAnnouncement": "<speak><amazon:effect name=\"drc\"><prosody rate=\"1.08\">Drive south on 9th Street. Then, in 600 feet, Turn left onto N Street.<\/prosody><\/amazon:effect><\/speak>",
                  "announcement": "Drive south on 9th Street. Then, in 600 feet, Turn left onto N Street.",
                  "distanceAlongGeometry": 182.142
                },
                {
                  "ssmlAnnouncement": "<speak><amazon:effect name=\"drc\"><prosody rate=\"1.08\">Turn left onto N Street, U.S. 40 Historic.<\/prosody><\/amazon:effect><\/speak>",
                  "announcement": "Turn left onto N Street, U.S. 40 Historic.",
                  "distanceAlongGeometry": 63.333
                }
              ],
              "intersections": [
                {
                  "entry": [
                    true
                  ],
                  "bearings": [
                    199
                  ],
                  "duration": 8.674,
                  "mapbox_streets_v8": {
                    "class": "street"
                  },
                  "is_urban": true,
                  "admin_index": 0,
                  "out": 0,
                  "weight": 10.626,
                  "geometry_index": 0,
                  "location": [
                    -121.496066,
                    38.577764
                  ]
                },
                {
                  "entry": [
                    false,
                    true
                  ],
                  "in": 0,
                  "bearings": [
                    19,
                    199
                  ],
                  "duration": 4.376,
                  "turn_weight": 2,
                  "turn_duration": 2.007,
                  "mapbox_streets_v8": {
                    "class": "street"
                  },
                  "is_urban": true,
                  "admin_index": 0,
                  "out": 1,
                  "weight": 4.901,
                  "geometry_index": 2,
                  "location": [
                    -121.496199,
                    38.577457
                  ]
                },
                {
                  "bearings": [
                    18,
                    199
                  ],
                  "entry": [
                    false,
                    true
                  ],
                  "in": 0,
                  "turn_weight": 2,
                  "turn_duration": 2.007,
                  "mapbox_streets_v8": {
                    "class": "street"
                  },
                  "is_urban": true,
                  "admin_index": 0,
                  "out": 1,
                  "geometry_index": 4,
                  "location": [
                    -121.496289,
                    38.577247
                  ]
                }
              ],
              "bannerInstructions": [
                {
                  "primary": {
                    "components": [
                      {
                        "type": "text",
                        "text": "N Street"
                      },
                      {
                        "type": "delimiter",
                        "text": "\/"
                      },
                      {
                        "type": "icon",
                        "text": "US 40 Historic"
                      }
                    ],
                    "type": "turn",
                    "modifier": "left",
                    "text": "N Street \/ US 40 Historic"
                  },
                  "distanceAlongGeometry": 182.142
                }
              ],
              "speedLimitUnit": "mph",
              "maneuver": {
                "type": "depart",
                "instruction": "Drive south on 9th Street.",
                "bearing_after": 199,
                "bearing_before": 0,
                "location": [
                  -121.496066,
                  38.577764
                ]
              },
              "speedLimitSign": "mutcd",
              "name": "9th Street",
              "weight_typical": 33.221,
              "duration_typical": 27.869,
              "duration": 27.869,
              "distance": 182.142,
              "driving_side": "right",
              "weight": 33.221,
              "mode": "driving",
              "geometry": "gerqhAb_pvfFlMfEvC`A`F`B`EpAtDnAny@bX"
            },
            {
              "voiceInstructions": [
                {
                  "ssmlAnnouncement": "<speak><amazon:effect name=\"drc\"><prosody rate=\"1.08\">Continue for a half mile.<\/prosody><\/amazon:effect><\/speak>",
                  "announcement": "Continue for a half mile.",
                  "distanceAlongGeometry": 868.667
                },
                {
                  "ssmlAnnouncement": "<speak><amazon:effect name=\"drc\"><prosody rate=\"1.08\">In a quarter mile, Turn left onto 16th Street.<\/prosody><\/amazon:effect><\/speak>",
                  "announcement": "In a quarter mile, Turn left onto 16th Street.",
                  "distanceAlongGeometry": 402.336
                },
                {
                  "ssmlAnnouncement": "<speak><amazon:effect name=\"drc\"><prosody rate=\"1.08\">Turn left onto 16th Street, California 1 60.<\/prosody><\/amazon:effect><\/speak>",
                  "announcement": "Turn left onto 16th Street, California 1 60.",
                  "distanceAlongGeometry": 80
                }
              ],
              "intersections": [
                {
                  "entry": [
                    false,
                    true
                  ],
                  "in": 0,
                  "bearings": [
                    19,
                    109
                  ],
                  "duration": 25.358,
                  "turn_weight": 20,
                  "turn_duration": 5.395,
                  "mapbox_streets_v8": {
                    "class": "secondary"
                  },
                  "is_urban": true,
                  "admin_index": 0,
                  "out": 1,
                  "weight": 44.455,
                  "geometry_index": 6,
                  "location": [
                    -121.496731,
                    38.57622
                  ]
                },
                {
                  "entry": [
                    true,
                    false
                  ],
                  "in": 1,
                  "bearings": [
                    109,
                    289
                  ],
                  "duration": 0.739,
                  "turn_weight": 2,
                  "turn_duration": 0.019,
                  "mapbox_streets_v8": {
                    "class": "secondary"
                  },
                  "is_urban": true,
                  "admin_index": 0,
                  "out": 0,
                  "weight": 2.882,
                  "geometry_index": 7,
                  "location": [
                    -121.495405,
                    38.57587
                  ]
                },
                {
                  "entry": [
                    true,
                    false
                  ],
                  "in": 1,
                  "bearings": [
                    110,
                    289
                  ],
                  "duration": 0.419,
                  "turn_weight": 2,
                  "turn_duration": 0.007,
                  "mapbox_streets_v8": {
                    "class": "secondary"
                  },
                  "is_urban": true,
                  "admin_index": 0,
                  "out": 0,
                  "weight": 2.504,
                  "geometry_index": 8,
                  "location": [
                    -121.49533,
                    38.57585
                  ]
                },
                {
                  "entry": [
                    true,
                    false
                  ],
                  "in": 1,
                  "bearings": [
                    109,
                    290
                  ],
                  "duration": 10.306,
                  "turn_weight": 0.5,
                  "turn_duration": 0.021,
                  "mapbox_streets_v8": {
                    "class": "secondary"
                  },
                  "is_urban": true,
                  "admin_index": 0,
                  "out": 0,
                  "weight": 13.1,
                  "geometry_index": 9,
                  "location": [
                    -121.495287,
                    38.575838
                  ]
                },
                {
                  "entry": [
                    true,
                    false
                  ],
                  "in": 1,
                  "bearings": [
                    110,
                    289
                  ],
                  "duration": 1.139,
                  "turn_weight": 0.5,
                  "turn_duration": 0.007,
                  "mapbox_streets_v8": {
                    "class": "secondary"
                  },
                  "is_urban": true,
                  "admin_index": 0,
                  "out": 0,
                  "weight": 1.886,
                  "geometry_index": 10,
                  "location": [
                    -121.494198,
                    38.575543
                  ]
                },
                {
                  "entry": [
                    true,
                    false
                  ],
                  "in": 1,
                  "bearings": [
                    108,
                    290
                  ],
                  "duration": 1.487,
                  "turn_weight": 0.5,
                  "turn_duration": 0.021,
                  "mapbox_streets_v8": {
                    "class": "secondary"
                  },
                  "is_urban": true,
                  "admin_index": 0,
                  "out": 0,
                  "weight": 2.297,
                  "geometry_index": 11,
                  "location": [
                    -121.494083,
                    38.575511
                  ]
                },
                {
                  "entry": [
                    true,
                    false
                  ],
                  "in": 1,
                  "bearings": [
                    109,
                    288
                  ],
                  "duration": 13.619,
                  "turn_weight": 0.5,
                  "turn_duration": 0.019,
                  "mapbox_streets_v8": {
                    "class": "secondary"
                  },
                  "is_urban": true,
                  "admin_index": 0,
                  "out": 0,
                  "weight": 17.16,
                  "geometry_index": 12,
                  "location": [
                    -121.49396,
                    38.57548
                  ]
                },
                {
                  "entry": [
                    true,
                    false
                  ],
                  "in": 1,
                  "bearings": [
                    112,
                    289
                  ],
                  "duration": 1.342,
                  "turn_weight": 0.5,
                  "turn_duration": 0.009,
                  "mapbox_streets_v8": {
                    "class": "secondary"
                  },
                  "is_urban": true,
                  "admin_index": 0,
                  "out": 0,
                  "weight": 2.133,
                  "geometry_index": 13,
                  "location": [
                    -121.492854,
                    38.575189
                  ]
                },
                {
                  "entry": [
                    true,
                    false
                  ],
                  "in": 1,
                  "bearings": [
                    106,
                    292
                  ],
                  "duration": 0.904,
                  "turn_weight": 2,
                  "turn_duration": 0.026,
                  "mapbox_streets_v8": {
                    "class": "secondary"
                  },
                  "is_urban": true,
                  "admin_index": 0,
                  "out": 0,
                  "weight": 3.076,
                  "geometry_index": 14,
                  "location": [
                    -121.492745,
                    38.575155
                  ]
                },
                {
                  "entry": [
                    true,
                    false
                  ],
                  "in": 1,
                  "bearings": [
                    109,
                    286
                  ],
                  "duration": 11.159,
                  "turn_weight": 0.5,
                  "turn_duration": 0.008,
                  "mapbox_streets_v8": {
                    "class": "secondary"
                  },
                  "is_urban": true,
                  "admin_index": 0,
                  "out": 0,
                  "weight": 14.16,
                  "geometry_index": 15,
                  "location": [
                    -121.492633,
                    38.57513
                  ]
                },
                {
                  "entry": [
                    true,
                    false
                  ],
                  "in": 1,
                  "bearings": [
                    109,
                    289
                  ],
                  "duration": 0.985,
                  "turn_weight": 0.5,
                  "turn_duration": 0.019,
                  "mapbox_streets_v8": {
                    "class": "secondary"
                  },
                  "is_urban": true,
                  "admin_index": 0,
                  "out": 0,
                  "weight": 1.683,
                  "geometry_index": 16,
                  "location": [
                    -121.491254,
                    38.574763
                  ]
                },
                {
                  "entry": [
                    true,
                    false
                  ],
                  "in": 1,
                  "bearings": [
                    109,
                    289
                  ],
                  "duration": 0.723,
                  "turn_weight": 2,
                  "turn_duration": 0.019,
                  "mapbox_streets_v8": {
                    "class": "secondary"
                  },
                  "is_urban": true,
                  "admin_index": 0,
                  "out": 0,
                  "weight": 2.863,
                  "geometry_index": 17,
                  "location": [
                    -121.491134,
                    38.574731
                  ]
                },
                {
                  "entry": [
                    true,
                    false
                  ],
                  "in": 1,
                  "bearings": [
                    109,
                    289
                  ],
                  "duration": 8.002,
                  "turn_weight": 0.5,
                  "turn_duration": 0.019,
                  "mapbox_streets_v8": {
                    "class": "secondary"
                  },
                  "is_urban": true,
                  "admin_index": 0,
                  "out": 0,
                  "weight": 10.279,
                  "geometry_index": 18,
                  "location": [
                    -121.491033,
                    38.574704
                  ]
                },
                {
                  "entry": [
                    true,
                    false
                  ],
                  "in": 1,
                  "bearings": [
                    109,
                    289
                  ],
                  "duration": 0.88,
                  "turn_weight": 2,
                  "turn_duration": 0.019,
                  "mapbox_streets_v8": {
                    "class": "secondary"
                  },
                  "is_urban": true,
                  "admin_index": 0,
                  "out": 0,
                  "weight": 3.055,
                  "geometry_index": 19,
                  "location": [
                    -121.489923,
                    38.574409
                  ]
                },
                {
                  "entry": [
                    true,
                    false
                  ],
                  "in": 1,
                  "bearings": [
                    109,
                    289
                  ],
                  "duration": 1.603,
                  "turn_weight": 0.5,
                  "turn_duration": 0.019,
                  "mapbox_streets_v8": {
                    "class": "secondary"
                  },
                  "is_urban": true,
                  "admin_index": 0,
                  "out": 0,
                  "weight": 2.44,
                  "geometry_index": 20,
                  "location": [
                    -121.489802,
                    38.574377
                  ]
                },
                {
                  "entry": [
                    true,
                    false
                  ],
                  "in": 1,
                  "bearings": [
                    109,
                    289
                  ],
                  "duration": 16.003,
                  "turn_weight": 2,
                  "turn_duration": 0.019,
                  "mapbox_streets_v8": {
                    "class": "secondary"
                  },
                  "is_urban": true,
                  "admin_index": 0,
                  "out": 0,
                  "weight": 21.58,
                  "geometry_index": 21,
                  "location": [
                    -121.489677,
                    38.574344
                  ]
                },
                {
                  "entry": [
                    true,
                    false
                  ],
                  "in": 1,
                  "bearings": [
                    108,
                    289
                  ],
                  "duration": 6.246,
                  "turn_weight": 2,
                  "turn_duration": 0.019,
                  "mapbox_streets_v8": {
                    "class": "secondary"
                  },
                  "is_urban": true,
                  "admin_index": 0,
                  "out": 0,
                  "weight": 9.628,
                  "geometry_index": 22,
                  "location": [
                    -121.488475,
                    38.574024
                  ]
                },
                {
                  "bearings": [
                    110,
                    288
                  ],
                  "entry": [
                    true,
                    false
                  ],
                  "in": 1,
                  "turn_weight": 0.5,
                  "turn_duration": 0.007,
                  "mapbox_streets_v8": {
                    "class": "secondary"
                  },
                  "is_urban": true,
                  "admin_index": 0,
                  "out": 0,
                  "geometry_index": 23,
                  "location": [
                    -121.487777,
                    38.573846
                  ]
                }
              ],
              "bannerInstructions": [
                {
                  "primary": {
                    "components": [
                      {
                        "type": "text",
                        "text": "16th Street"
                      },
                      {
                        "type": "delimiter",
                        "text": "\/"
                      },
                      {
                        "imageBaseURL": "https:\/\/mapbox-navigation-shields.s3.amazonaws.com\/public\/shields\/v4\/US\/ca-160",
                        "type": "icon",
                        "text": "CA 160"
                      }
                    ],
                    "type": "turn",
                    "modifier": "left",
                    "text": "16th Street \/ CA 160"
                  },
                  "distanceAlongGeometry": 882
                }
              ],
              "speedLimitUnit": "mph",
              "maneuver": {
                "type": "turn",
                "instruction": "Turn left onto N Street\/US 40 Historic.",
                "modifier": "left",
                "bearing_after": 109,
                "bearing_before": 199,
                "location": [
                  -121.496731,
                  38.57622
                ]
              },
              "speedLimitSign": "mutcd",
              "name": "N Street",
              "weight_typical": 168.071,
              "duration_typical": 111.038,
              "duration": 111.038,
              "distance": 882,
              "driving_side": "right",
              "weight": 168.071,
              "mode": "driving",
              "ref": "US 40 Historic",
              "geometry": "wdoqhAthqvfFzT{qAf@uCVuAlQacA~@eF|@uFdQcdAbAyEp@_F|UeuA~@oFt@iElQkdA~@qF`AyF~RcjAbJsj@`Juf@"
            },
            {
              "voiceInstructions": [
                {
                  "ssmlAnnouncement": "<speak><amazon:effect name=\"drc\"><prosody rate=\"1.08\">In a quarter mile, Turn right onto J Street.<\/prosody><\/amazon:effect><\/speak>",
                  "announcement": "In a quarter mile, Turn right onto J Street.",
                  "distanceAlongGeometry": 508.666
                },
                {
                  "ssmlAnnouncement": "<speak><amazon:effect name=\"drc\"><prosody rate=\"1.08\">Turn right onto J Street.<\/prosody><\/amazon:effect><\/speak>",
                  "announcement": "Turn right onto J Street.",
                  "distanceAlongGeometry": 66.667
                }
              ],
              "intersections": [
                {
                  "entry": [
                    true,
                    false
                  ],
                  "in": 1,
                  "bearings": [
                    19,
                    290
                  ],
                  "duration": 12.022,
                  "turn_weight": 7.5,
                  "turn_duration": 5.622,
                  "mapbox_streets_v8": {
                    "class": "secondary"
                  },
                  "is_urban": true,
                  "admin_index": 0,
                  "out": 0,
                  "weight": 15.34,
                  "geometry_index": 24,
                  "location": [
                    -121.487142,
                    38.573669
                  ]
                },
                {
                  "entry": [
                    true,
                    false
                  ],
                  "in": 1,
                  "bearings": [
                    19,
                    199
                  ],
                  "duration": 4.45,
                  "turn_weight": 2,
                  "turn_duration": 0.019,
                  "mapbox_streets_v8": {
                    "class": "secondary"
                  },
                  "is_urban": true,
                  "admin_index": 0,
                  "out": 0,
                  "weight": 7.428,
                  "geometry_index": 25,
                  "location": [
                    -121.486904,
                    38.574216
                  ]
                },
                {
                  "entry": [
                    true,
                    false
                  ],
                  "in": 1,
                  "bearings": [
                    19,
                    199
                  ],
                  "duration": 1.991,
                  "turn_weight": 2,
                  "turn_duration": 0.019,
                  "mapbox_streets_v8": {
                    "class": "secondary"
                  },
                  "is_urban": true,
                  "admin_index": 0,
                  "out": 0,
                  "weight": 4.415,
                  "geometry_index": 26,
                  "location": [
                    -121.486726,
                    38.574626
                  ]
                },
                {
                  "entry": [
                    true,
                    false
                  ],
                  "in": 1,
                  "bearings": [
                    19,
                    199
                  ],
                  "duration": 1.305,
                  "turn_weight": 0.5,
                  "turn_duration": 0.019,
                  "mapbox_streets_v8": {
                    "class": "secondary"
                  },
                  "is_urban": true,
                  "admin_index": 0,
                  "out": 0,
                  "weight": 2.075,
                  "geometry_index": 28,
                  "location": [
                    -121.486643,
                    38.574818
                  ]
                },
                {
                  "entry": [
                    true,
                    false
                  ],
                  "in": 1,
                  "bearings": [
                    18,
                    199
                  ],
                  "duration": 12.844,
                  "turn_weight": 2,
                  "turn_duration": 0.019,
                  "mapbox_streets_v8": {
                    "class": "secondary"
                  },
                  "is_urban": true,
                  "admin_index": 0,
                  "out": 0,
                  "weight": 17.711,
                  "geometry_index": 29,
                  "location": [
                    -121.486588,
                    38.574942
                  ]
                },
                {
                  "entry": [
                    true,
                    false
                  ],
                  "in": 1,
                  "bearings": [
                    18,
                    198
                  ],
                  "duration": 3.965,
                  "turn_weight": 2,
                  "turn_duration": 2.019,
                  "mapbox_streets_v8": {
                    "class": "secondary"
                  },
                  "is_urban": true,
                  "admin_index": 0,
                  "out": 0,
                  "weight": 4.384,
                  "geometry_index": 30,
                  "location": [
                    -121.486187,
                    38.575916
                  ]
                },
                {
                  "entry": [
                    true,
                    false
                  ],
                  "in": 1,
                  "bearings": [
                    18,
                    198
                  ],
                  "duration": 4.495,
                  "turn_weight": 0.5,
                  "turn_duration": 0.019,
                  "mapbox_streets_v8": {
                    "class": "secondary"
                  },
                  "is_urban": true,
                  "admin_index": 0,
                  "out": 0,
                  "weight": 5.983,
                  "geometry_index": 31,
                  "location": [
                    -121.486117,
                    38.576083
                  ]
                },
                {
                  "entry": [
                    true,
                    false
                  ],
                  "in": 1,
                  "bearings": [
                    19,
                    198
                  ],
                  "duration": 6.602,
                  "turn_weight": 2,
                  "turn_duration": 0.019,
                  "mapbox_streets_v8": {
                    "class": "secondary"
                  },
                  "is_urban": true,
                  "admin_index": 0,
                  "out": 0,
                  "weight": 10.064,
                  "geometry_index": 32,
                  "location": [
                    -121.485951,
                    38.576472
                  ]
                },
                {
                  "entry": [
                    true,
                    false
                  ],
                  "in": 1,
                  "bearings": [
                    19,
                    199
                  ],
                  "duration": 4.359,
                  "turn_weight": 2,
                  "turn_duration": 2.019,
                  "mapbox_streets_v8": {
                    "class": "secondary"
                  },
                  "is_urban": true,
                  "admin_index": 0,
                  "out": 0,
                  "weight": 4.866,
                  "geometry_index": 33,
                  "location": [
                    -121.485713,
                    38.577019
                  ]
                },
                {
                  "entry": [
                    true,
                    false
                  ],
                  "in": 1,
                  "bearings": [
                    20,
                    199
                  ],
                  "duration": 3.427,
                  "turn_weight": 0.5,
                  "turn_duration": 0.007,
                  "mapbox_streets_v8": {
                    "class": "secondary"
                  },
                  "is_urban": true,
                  "admin_index": 0,
                  "out": 0,
                  "weight": 4.69,
                  "geometry_index": 34,
                  "location": [
                    -121.485616,
                    38.577244
                  ]
                },
                {
                  "bearings": [
                    19,
                    200
                  ],
                  "entry": [
                    true,
                    false
                  ],
                  "in": 1,
                  "turn_weight": 2,
                  "turn_duration": 0.021,
                  "mapbox_streets_v8": {
                    "class": "secondary"
                  },
                  "is_urban": true,
                  "admin_index": 0,
                  "out": 0,
                  "geometry_index": 35,
                  "location": [
                    -121.485467,
                    38.577569
                  ]
                }
              ],
              "bannerInstructions": [
                {
                  "primary": {
                    "components": [
                      {
                        "type": "text",
                        "text": "J Street"
                      }
                    ],
                    "type": "turn",
                    "modifier": "right",
                    "text": "J Street"
                  },
                  "distanceAlongGeometry": 522
                }
              ],
              "speedLimitUnit": "mph",
              "maneuver": {
                "type": "turn",
                "instruction": "Turn left onto 16th Street\/CA 160\/US 40 Historic.",
                "modifier": "left",
                "bearing_after": 19,
                "bearing_before": 110,
                "location": [
                  -121.487142,
                  38.573669
                ]
              },
              "speedLimitSign": "mutcd",
              "name": "16th Street",
              "weight_typical": 93.067,
              "duration_typical": 67,
              "duration": 67,
              "distance": 522,
              "driving_side": "right",
              "weight": 93.067,
              "mode": "driving",
              "ref": "CA 160; US 40 Historic",
              "geometry": "iejqhAjq~ufFea@{MsXcJ_IkC_AYwFmB{{@aXmIkCiWkIea@{MaMaEiSiHia@uM"
            },
            {
              "voiceInstructions": [
                {
                  "ssmlAnnouncement": "<speak><amazon:effect name=\"drc\"><prosody rate=\"1.08\">In a quarter mile, Your destination will be on the right.<\/prosody><\/amazon:effect><\/speak>",
                  "announcement": "In a quarter mile, Your destination will be on the right.",
                  "distanceAlongGeometry": 443.209
                },
                {
                  "ssmlAnnouncement": "<speak><amazon:effect name=\"drc\"><prosody rate=\"1.08\">Your destination is on the right.<\/prosody><\/amazon:effect><\/speak>",
                  "announcement": "Your destination is on the right.",
                  "distanceAlongGeometry": 68.056
                }
              ],
              "intersections": [
                {
                  "entry": [
                    true,
                    false
                  ],
                  "in": 1,
                  "bearings": [
                    109,
                    199
                  ],
                  "duration": 8.107,
                  "turn_weight": 8,
                  "turn_duration": 4.005,
                  "mapbox_streets_v8": {
                    "class": "secondary"
                  },
                  "is_urban": true,
                  "admin_index": 0,
                  "out": 0,
                  "weight": 13.025,
                  "geometry_index": 36,
                  "location": [
                    -121.485232,
                    38.578118
                  ]
                },
                {
                  "entry": [
                    true,
                    false
                  ],
                  "in": 1,
                  "bearings": [
                    108,
                    289
                  ],
                  "duration": 2.698,
                  "turn_weight": 0.5,
                  "turn_duration": 0.019,
                  "mapbox_streets_v8": {
                    "class": "secondary"
                  },
                  "is_urban": true,
                  "admin_index": 0,
                  "out": 0,
                  "weight": 3.782,
                  "geometry_index": 37,
                  "location": [
                    -121.484704,
                    38.577976
                  ]
                },
                {
                  "entry": [
                    true,
                    false
                  ],
                  "in": 1,
                  "bearings": [
                    109,
                    288
                  ],
                  "duration": 0.739,
                  "turn_weight": 0.5,
                  "turn_duration": 0.019,
                  "mapbox_streets_v8": {
                    "class": "secondary"
                  },
                  "is_urban": true,
                  "admin_index": 0,
                  "out": 0,
                  "weight": 1.382,
                  "geometry_index": 38,
                  "location": [
                    -121.48436,
                    38.577887
                  ]
                },
                {
                  "entry": [
                    true,
                    false
                  ],
                  "in": 1,
                  "bearings": [
                    109,
                    289
                  ],
                  "duration": 2.251,
                  "turn_weight": 0.5,
                  "turn_duration": 0.019,
                  "mapbox_streets_v8": {
                    "class": "secondary"
                  },
                  "is_urban": true,
                  "admin_index": 0,
                  "out": 0,
                  "weight": 3.234,
                  "geometry_index": 39,
                  "location": [
                    -121.484255,
                    38.577859
                  ]
                },
                {
                  "entry": [
                    true,
                    false
                  ],
                  "in": 1,
                  "bearings": [
                    109,
                    289
                  ],
                  "duration": 5.766,
                  "turn_weight": 2,
                  "turn_duration": 2.019,
                  "mapbox_streets_v8": {
                    "class": "secondary"
                  },
                  "is_urban": true,
                  "admin_index": 0,
                  "out": 0,
                  "weight": 6.59,
                  "geometry_index": 40,
                  "location": [
                    -121.483923,
                    38.57777
                  ]
                },
                {
                  "entry": [
                    true,
                    false
                  ],
                  "in": 1,
                  "bearings": [
                    109,
                    289
                  ],
                  "duration": 1.048,
                  "turn_weight": 0.5,
                  "turn_duration": 0.019,
                  "mapbox_streets_v8": {
                    "class": "secondary"
                  },
                  "is_urban": true,
                  "admin_index": 0,
                  "out": 0,
                  "weight": 1.76,
                  "geometry_index": 41,
                  "location": [
                    -121.48337,
                    38.577623
                  ]
                },
                {
                  "entry": [
                    true,
                    false
                  ],
                  "in": 1,
                  "bearings": [
                    109,
                    289
                  ],
                  "duration": 3.805,
                  "turn_weight": 0.5,
                  "turn_duration": 0.019,
                  "mapbox_streets_v8": {
                    "class": "secondary"
                  },
                  "is_urban": true,
                  "admin_index": 0,
                  "out": 0,
                  "weight": 5.138,
                  "geometry_index": 42,
                  "location": [
                    -121.48322,
                    38.577583
                  ]
                },
                {
                  "entry": [
                    true,
                    false
                  ],
                  "in": 1,
                  "bearings": [
                    109,
                    289
                  ],
                  "duration": 12.476,
                  "turn_weight": 2,
                  "turn_duration": 2.019,
                  "mapbox_streets_v8": {
                    "class": "secondary"
                  },
                  "is_urban": true,
                  "admin_index": 0,
                  "out": 0,
                  "weight": 14.81,
                  "geometry_index": 43,
                  "location": [
                    -121.482552,
                    38.577406
                  ]
                },
                {
                  "entry": [
                    true,
                    false
                  ],
                  "in": 1,
                  "bearings": [
                    109,
                    289
                  ],
                  "duration": 5.516,
                  "turn_weight": 2,
                  "turn_duration": 2.019,
                  "mapbox_streets_v8": {
                    "class": "secondary"
                  },
                  "is_urban": true,
                  "admin_index": 0,
                  "out": 0,
                  "weight": 6.284,
                  "geometry_index": 44,
                  "location": [
                    -121.481224,
                    38.577052
                  ]
                },
                {
                  "entry": [
                    true,
                    false
                  ],
                  "in": 1,
                  "bearings": [
                    109,
                    289
                  ],
                  "duration": 3.196,
                  "turn_weight": 0.5,
                  "turn_duration": 0.019,
                  "mapbox_streets_v8": {
                    "class": "secondary"
                  },
                  "is_urban": true,
                  "admin_index": 0,
                  "out": 0,
                  "weight": 4.391,
                  "geometry_index": 45,
                  "location": [
                    -121.480853,
                    38.576954
                  ]
                },
                {
                  "entry": [
                    true,
                    false
                  ],
                  "in": 1,
                  "bearings": [
                    109,
                    289
                  ],
                  "duration": 1.665,
                  "turn_weight": 0.5,
                  "turn_duration": 0.019,
                  "mapbox_streets_v8": {
                    "class": "secondary"
                  },
                  "is_urban": true,
                  "admin_index": 0,
                  "out": 0,
                  "weight": 2.516,
                  "geometry_index": 46,
                  "location": [
                    -121.480528,
                    38.576867
                  ]
                },
                {
                  "bearings": [
                    108,
                    289
                  ],
                  "entry": [
                    true,
                    false
                  ],
                  "in": 1,
                  "turn_weight": 0.5,
                  "turn_duration": 0.019,
                  "mapbox_streets_v8": {
                    "class": "secondary"
                  },
                  "is_urban": true,
                  "admin_index": 0,
                  "out": 0,
                  "geometry_index": 48,
                  "location": [
                    -121.480356,
                    38.576821
                  ]
                }
              ],
              "bannerInstructions": [
                {
                  "primary": {
                    "components": [
                      {
                        "type": "text",
                        "text": "Your destination will be on the right"
                      }
                    ],
                    "type": "arrive",
                    "modifier": "right",
                    "text": "Your destination will be on the right"
                  },
                  "distanceAlongGeometry": 459.209
                },
                {
                  "primary": {
                    "components": [
                      {
                        "type": "text",
                        "text": "Your destination is on the right"
                      }
                    ],
                    "type": "arrive",
                    "modifier": "right",
                    "text": "Your destination is on the right"
                  },
                  "distanceAlongGeometry": 68.056
                }
              ],
              "speedLimitUnit": "mph",
              "maneuver": {
                "type": "turn",
                "instruction": "Turn right onto J Street.",
                "modifier": "right",
                "bearing_after": 109,
                "bearing_before": 19,
                "location": [
                  -121.485232,
                  38.578118
                ]
              },
              "speedLimitSign": "mutcd",
              "name": "J Street",
              "weight_typical": 71.754,
              "duration_typical": 54.096,
              "duration": 48.262,
              "distance": 459.209,
              "driving_side": "right",
              "weight": 64.607,
              "mode": "driving",
              "geometry": "k{rqhA~yzufFzG_`@pDoTv@qEpDwSdHqa@nAkH`Jwh@bU_rAbEeVlDiSj@iDn@mDr@gE"
            },
            {
              "voiceInstructions": [],
              "intersections": [
                {
                  "bearings": [
                    288
                  ],
                  "entry": [
                    true
                  ],
                  "in": 0,
                  "admin_index": 0,
                  "geometry_index": 49,
                  "location": [
                    -121.480256,
                    38.576795
                  ]
                }
              ],
              "bannerInstructions": [],
              "speedLimitUnit": "mph",
              "maneuver": {
                "type": "arrive",
                "instruction": "Your destination is on the right.",
                "modifier": "right",
                "bearing_after": 0,
                "bearing_before": 108,
                "location": [
                  -121.480256,
                  38.576795
                ]
              },
              "speedLimitSign": "mutcd",
              "name": "J Street",
              "weight_typical": 0,
              "duration_typical": 0,
              "duration": 0,
              "distance": 0,
              "driving_side": "right",
              "weight": 0,
              "mode": "driving",
              "geometry": "uhpqhA~bqufF??"
            }
          ],
          "distance": 2045.35,
          "summary": "N Street, 16th Street"
        }
      ],
      "geometry": "gerqhAb_pvfFlMfEvC`A`F`B`EpAtDnAny@bXzT{qAf@uCVuAlQacA~@eF|@uFdQcdAbAyEp@_F|UeuA~@oFt@iElQkdA~@qF`AyF~RcjAbJsj@`Juf@ea@{MsXcJ_IkC_AYwFmB{{@aXmIkCiWkIea@{MaMaEiSiHia@uMzG_`@pDoTv@qEpDwSdHqa@nAkH`Jwh@bU_rAbEeVlDiSj@iDn@mDr@gE",
      "voiceLocale": "en-US"
    }
  ],
  "waypoints": [
    {
      "distance": 8.347,
      "name": "9th Street",
      "location": [
        -121.496066,
        38.577764
      ]
    },
    {
      "distance": 6.435,
      "name": "J Street",
      "location": [
        -121.480256,
        38.576795
      ]
    }
  ],
  "code": "Ok",
  "uuid": "route_response_single_route_refresh_without_traffic"
}